acmepcap.py
acmepcap-0.1.0.dist-info/licenses/LICENSE
acmepcap-0.1.0.dist-info/METADATA
acmepcap-0.1.0.dist-info/WHEEL
acmepcap-0.1.0.dist-info/entry_points.txt
acmepcap-0.1.0.dist-info/top_level.txt
acmepcap-0.1.0.dist-info/RECORD
