Metadata-Version: 2.4
Name: acmepcap
Version: 0.1.0
Summary: Acme Packet sipmsg.log to packet capture converter.
Author-email: Andrzej Mateja <mateja.and@gmail.com>
License-Expression: MIT
Project-URL: Homepage, https://github.com/amateja/acmepcap/
Keywords: Acme,AcmePacket,SBC,sipmsg
Classifier: Development Status :: 4 - Beta
Classifier: Programming Language :: Python :: 3.9
Classifier: Programming Language :: Python :: 3.10
Classifier: Programming Language :: Python :: 3.11
Classifier: Programming Language :: Python :: 3.12
Classifier: Programming Language :: Python :: 3.13
Classifier: Programming Language :: Python :: 3.14
Classifier: Programming Language :: Python :: 3.15
Classifier: Operating System :: OS Independent
Classifier: Topic :: Utilities
Requires-Python: >=3.9
License-File: LICENSE
Dynamic: license-file
